odoo/addons/purchase_stock_product_replenish_supplier/README.rst
odoo/addons/purchase_stock_product_replenish_supplier/__init__.py
odoo/addons/purchase_stock_product_replenish_supplier/__manifest__.py
odoo/addons/purchase_stock_product_replenish_supplier/i18n/it.po
odoo/addons/purchase_stock_product_replenish_supplier/i18n/purchase_stock_product_replenish_supplier.pot
odoo/addons/purchase_stock_product_replenish_supplier/readme/CONTRIBUTORS.md
odoo/addons/purchase_stock_product_replenish_supplier/readme/DESCRIPTION.md
odoo/addons/purchase_stock_product_replenish_supplier/static/description/icon.png
odoo/addons/purchase_stock_product_replenish_supplier/static/description/index.html
odoo/addons/purchase_stock_product_replenish_supplier/tests/__init__.py
odoo/addons/purchase_stock_product_replenish_supplier/tests/test_product_replenish.py
odoo/addons/purchase_stock_product_replenish_supplier/wizards/__init__.py
odoo/addons/purchase_stock_product_replenish_supplier/wizards/product_replenish.py
odoo_addon_purchase_stock_product_replenish_supplier-18.0.1.0.0.4.dist-info/METADATA
odoo_addon_purchase_stock_product_replenish_supplier-18.0.1.0.0.4.dist-info/WHEEL
odoo_addon_purchase_stock_product_replenish_supplier-18.0.1.0.0.4.dist-info/top_level.txt
odoo_addon_purchase_stock_product_replenish_supplier-18.0.1.0.0.4.dist-info/RECORD
