Metadata-Version: 2.1
Name: odoo-addon-purchase_stock_product_replenish_supplier
Version: 18.0.1.0.0.4
Requires-Python: >=3.10
Requires-Dist: odoo==18.0.*
Summary: Set default supplier in product replenish wizard
Home-page: https://github.com/OCA/stock-logistics-orderpoint
License: AGPL-3
Author: BCIM, Odoo Community Association (OCA)
Author-email: support@odoo-community.org
Classifier: Programming Language :: Python
Classifier: Framework :: Odoo
Classifier: Framework :: Odoo :: 18.0
Classifier: License :: OSI Approved :: GNU Affero General Public License v3
Classifier: Development Status :: 3 - Alpha
